pandas_contract/__init__.py
pandas_contract/_decorator.py
pandas_contract/_lib.py
pandas_contract/_private_checks.py
pandas_contract/checks.py
pandas_contract/mode.py
pandas_contract/py.typed
pandas_contract-0.11.4.dist-info/METADATA
pandas_contract-0.11.4.dist-info/WHEEL
pandas_contract-0.11.4.dist-info/licenses/LICENSE
pandas_contract-0.11.4.dist-info/RECORD
