Metadata-Version: 2.4
Name: pandas-contract
Version: 0.11.4
Summary: Define input and output columns for functions working on pandas dataframes.
Project-URL: homepage, https://pandas-contract.readthedocs.io/en/latest/
Project-URL: issues, https://github.com/schollm/pandas-contract/projects
Project-URL: source, https://github.com/schollm/pandas-contract
Project-URL: changelog, https://github.com/schollm/pandas-contract/blob/main/CHANGELOG.md
Project-URL: documentation, https://pandas-contract.readthedocs.io/en/latest/
Author-email: Micha Scholl <schollm-git@gmx.com>
License-File: LICENSE
Keywords: contract,dependencies,pandas,pandera,validation
Classifier: Development Status :: 4 - Beta
Classifier: Intended Audience :: Developers
Classifier: License :: OSI Approved :: MIT License
Classifier: Programming Language :: Python :: 3
Classifier: Programming Language :: Python :: 3.9
Classifier: Programming Language :: Python :: 3.10
Classifier: Programming Language :: Python :: 3.11
Classifier: Programming Language :: Python :: 3.12
Classifier: Programming Language :: Python :: 3.13
Classifier: Programming Language :: Python :: 3.14
Classifier: Programming Language :: Python :: Implementation :: CPython
Classifier: Programming Language :: Python :: Implementation :: PyPy
Classifier: Topic :: Documentation
Classifier: Topic :: Software Development :: Libraries :: Python Modules
Classifier: Topic :: Software Development :: Testing
Classifier: Typing :: Typed
Requires-Python: >=3.9
Requires-Dist: pandas>=1.5.0
Requires-Dist: pandera[pandas]>=0.22.0
